topsis/__init__.py
topsis/topsis.py
Topsis_Anchit_102003117-0.0.13.dist-info/METADATA
Topsis_Anchit_102003117-0.0.13.dist-info/WHEEL
Topsis_Anchit_102003117-0.0.13.dist-info/top_level.txt
Topsis_Anchit_102003117-0.0.13.dist-info/RECORD
