Metadata-Version: 2.1
Name: Topsis-Anchit-102003117
Version: 0.0.13
Summary: Topsis code for calculation 
Home-page: UNKNOWN
Author: Anchit Rana
Author-email: <arana2_be20@thapar.edu>
License: UNKNOWN
Platform: UNKNOWN
Classifier: Development Status :: 1 - Planning
Classifier: Intended Audience :: Developers
Classifier: Programming Language :: Python :: 3
Classifier: Operating System :: Unix
Classifier: Operating System :: MacOS :: MacOS X
Classifier: Operating System :: Microsoft :: Windows
